helios_ls/__init__.py
helios_ls/completer.py
helios_ls/diagnostics.py
helios_ls/helios-language.so
helios_ls/helios_types.py
helios_ls/hlparser.py
helios_ls/hover.py
helios_ls/namespace.py
helios_ls/server.py
helios_ls/signature_helper.py
helios_language_server-0.3.1.dist-info/LICENSE
helios_language_server-0.3.1.dist-info/METADATA
helios_language_server-0.3.1.dist-info/WHEEL
helios_language_server-0.3.1.dist-info/entry_points.txt
helios_language_server-0.3.1.dist-info/RECORD
