Metadata-Version: 2.1
Name: helios-language-server
Version: 0.3.1
Summary: Language server for Helios, a non-Haskell Cardano smart contract DSL.
License: MIT
Keywords: cardano,helios,neovim,lsp
Author: et
Author-email: etet1997@hotmail.com
Requires-Python: >=3.7,<3.12
Classifier: License :: OSI Approved :: MIT License
Classifier: Programming Language :: Python :: 3
Classifier: Programming Language :: Python :: 3.7
Classifier: Programming Language :: Python :: 3.8
Classifier: Programming Language :: Python :: 3.9
Classifier: Programming Language :: Python :: 3.10
Classifier: Programming Language :: Python :: 3.11
Requires-Dist: loguru (>=0.6.0,<0.7.0)
Requires-Dist: pydantic (==1.10.2)
Requires-Dist: pygls (==0.13.1)
Requires-Dist: tree-sitter (>=0.20.1,<0.21.0)
